{
	"kind" : "toolchains",
	"toolchains" : 
	[
		{
			"compiler" : 
			{
				"id" : "NVIDIA",
				"implicit" : 
				{
					"includeDirectories" : [],
					"linkDirectories" : 
					[
						"D:/NVIDIA GPU Computing Toolkit/CUDA/v10.0/lib/x64"
					],
					"linkFrameworkDirectories" : [],
					"linkLibraries" : []
				},
				"path" : "D:/NVIDIA GPU Computing Toolkit/CUDA/v10.0/bin/nvcc.exe",
				"version" : "10.0.130"
			},
			"language" : "CUDA",
			"sourceFileExtensions" : 
			[
				"cu"
			]
		},
		{
			"compiler" : 
			{
				"implicit" : {},
				"path" : "C:/Program Files (x86)/Windows Kits/10/bin/10.0.17763.0/x64/rc.exe"
			},
			"language" : "RC",
			"sourceFileExtensions" : 
			[
				"rc",
				"RC"
			]
		}
	],
	"version" : 
	{
		"major" : 1,
		"minor" : 0
	}
}
